[
    {
        "position": [
            132,
            273
        ],
        "rgb": [
            128,
            113,
            89
        ],
        "intensity": 110.0,
        "mean_window": [
            132.23140495867767,
            113.49586776859505,
            76.01652892561984
        ],
        "std_window": [
            30.684952117541954,
            34.14870832762673,
            48.85397087848919
        ],
        "window": [
            [
                [
                    0,
                    255,
                    0
                ],
                [
                    0,
                    255,
                    0
                ],
                [
                    0,
                    255,
                    0
                ],
                [
                    0,
                    255,
                    0
                ],
                [
                    0,
                    255,
                    0
                ],
                [
                    0,
                    255,
                    0
                ],
                [
                    0,
                    255,
                    0
                ],
                [
                    0,
                    255,
                    0
                ],
                [
                    0,
                    255,
                    0
                ],
                [
                    0,
                    255,
                    0
                ],
                [
                    0,
                    255,
                    0
                ]
            ],
            [
                [
                    0,
                    255,
                    0
                ],
                [
                    96,
                    72,
                    8
                ],
                [
                    137,
                    113,
                    77
                ],
                [
                    149,
                    138,
                    121
                ],
                [
                    128,
                    113,
                    89
                ],
                [
                    125,
                    107,
                    79
                ],
                [
                    125,
                    107,
                    79
                ],
                [
                    125,
                    107,
                    79
                ],
                [
                    182,
                    167,
                    140
                ],
                [
                    227,
                    216,
                    195
                ],
                [
                    0,
                    255,
                    0
                ]
            ],
            [
                [
                    0,
                    255,
                    0
                ],
                [
                    96,
                    72,
                    8
                ],
                [
                    132,
                    100,
                    44
                ],
                [
                    162,
                    144,
                    113
                ],
                [
                    136,
                    119,
                    91
                ],
                [
                    125,
                    107,
                    79
                ],
                [
                    125,
                    107,
                    79
                ],
                [
                    125,
                    107,
                    79
                ],
                [
                    154,
                    137,
                    107
                ],
                [
                    238,
                    229,
                    211
                ],
                [
                    0,
                    255,
                    0
                ]
            ],
            [
                [
                    0,
                    255,
                    0
                ],
                [
                    96,
                    72,
                    8
                ],
                [
                    132,
                    100,
                    44
                ],
                [
                    154,
                    137,
                    107
                ],
                [
                    136,
                    119,
                    91
                ],
                [
                    128,
                    113,
                    89
                ],
                [
                    125,
                    107,
                    79
                ],
                [
                    125,
                    107,
                    79
                ],
                [
                    140,
                    127,
                    108
                ],
                [
                    220,
                    209,
                    187
                ],
                [
                    0,
                    255,
                    0
                ]
            ],
            [
                [
                    0,
                    255,
                    0
                ],
                [
                    96,
                    72,
                    8
                ],
                [
                    132,
                    100,
                    44
                ],
                [
                    154,
                    137,
                    107
                ],
                [
                    140,
                    127,
                    108
                ],
                [
                    128,
                    113,
                    89
                ],
                [
                    125,
                    107,
                    79
                ],
                [
                    125,
                    107,
                    79
                ],
                [
                    128,
                    113,
                    89
                ],
                [
                    185,
                    174,
                    151
                ],
                [
                    0,
                    255,
                    0
                ]
            ],
            [
                [
                    0,
                    255,
                    0
                ],
                [
                    96,
                    72,
                    8
                ],
                [
                    125,
                    103,
                    12
                ],
                [
                    149,
                    130,
                    100
                ],
                [
                    140,
                    127,
                    108
                ],
                [
                    128,
                    113,
                    89
                ],
                [
                    128,
                    113,
                    89
                ],
                [
                    125,
                    107,
                    79
                ],
                [
                    125,
                    107,
                    79
                ],
                [
                    149,
                    138,
                    121
                ],
                [
                    0,
                    255,
                    0
                ]
            ],
            [
                [
                    0,
                    255,
                    0
                ],
                [
                    96,
                    72,
                    8
                ],
                [
                    125,
                    103,
                    12
                ],
                [
                    155,
                    120,
                    73
                ],
                [
                    140,
                    127,
                    108
                ],
                [
                    136,
                    119,
                    91
                ],
                [
                    128,
                    113,
                    89
                ],
                [
                    125,
                    107,
                    79
                ],
                [
                    128,
                    113,
                    89
                ],
                [
                    128,
                    113,
                    89
                ],
                [
                    0,
                    255,
                    0
                ]
            ],
            [
                [
                    0,
                    255,
                    0
                ],
                [
                    96,
                    72,
                    8
                ],
                [
                    132,
                    100,
                    44
                ],
                [
                    145,
                    108,
                    54
                ],
                [
                    136,
                    119,
                    91
                ],
                [
                    140,
                    127,
                    108
                ],
                [
                    128,
                    113,
                    89
                ],
                [
                    125,
                    107,
                    79
                ],
                [
                    125,
                    107,
                    79
                ],
                [
                    125,
                    107,
                    79
                ],
                [
                    0,
                    255,
                    0
                ]
            ],
            [
                [
                    0,
                    255,
                    0
                ],
                [
                    96,
                    72,
                    8
                ],
                [
                    146,
                    117,
                    32
                ],
                [
                    132,
                    100,
                    44
                ],
                [
                    120,
                    100,
                    74
                ],
                [
                    149,
                    138,
                    121
                ],
                [
                    128,
                    113,
                    89
                ],
                [
                    125,
                    107,
                    79
                ],
                [
                    125,
                    107,
                    79
                ],
                [
                    128,
                    113,
                    89
                ],
                [
                    0,
                    255,
                    0
                ]
            ],
            [
                [
                    0,
                    255,
                    0
                ],
                [
                    88,
                    63,
                    7
                ],
                [
                    132,
                    100,
                    44
                ],
                [
                    125,
                    103,
                    12
                ],
                [
                    120,
                    88,
                    37
                ],
                [
                    154,
                    137,
                    107
                ],
                [
                    136,
                    119,
                    91
                ],
                [
                    125,
                    107,
                    79
                ],
                [
                    125,
                    107,
                    79
                ],
                [
                    128,
                    113,
                    89
                ],
                [
                    0,
                    255,
                    0
                ]
            ],
            [
                [
                    0,
                    255,
                    0
                ],
                [
                    0,
                    255,
                    0
                ],
                [
                    0,
                    255,
                    0
                ],
                [
                    0,
                    255,
                    0
                ],
                [
                    0,
                    255,
                    0
                ],
                [
                    0,
                    255,
                    0
                ],
                [
                    0,
                    255,
                    0
                ],
                [
                    0,
                    255,
                    0
                ],
                [
                    0,
                    255,
                    0
                ],
                [
                    0,
                    255,
                    0
                ],
                [
                    0,
                    255,
                    0
                ]
            ]
        ]
    },
    {
        "position": [
            132,
            273
        ],
        "rgb": [
            128,
            113,
            89
        ],
        "intensity": 110.0,
        "mean_window": [
            132.23140495867767,
            113.49586776859505,
            76.01652892561984
        ],
        "std_window": [
            30.684952117541954,
            34.14870832762673,
            48.85397087848919
        ],
        "window": [
            [
                [
                    0,
                    255,
                    0
                ],
                [
                    0,
                    255,
                    0
                ],
                [
                    0,
                    255,
                    0
                ],
                [
                    0,
                    255,
                    0
                ],
                [
                    0,
                    255,
                    0
                ],
                [
                    0,
                    255,
                    0
                ],
                [
                    0,
                    255,
                    0
                ],
                [
                    0,
                    255,
                    0
                ],
                [
                    0,
                    255,
                    0
                ],
                [
                    0,
                    255,
                    0
                ],
                [
                    0,
                    255,
                    0
                ]
            ],
            [
                [
                    0,
                    255,
                    0
                ],
                [
                    96,
                    72,
                    8
                ],
                [
                    137,
                    113,
                    77
                ],
                [
                    149,
                    138,
                    121
                ],
                [
                    128,
                    113,
                    89
                ],
                [
                    125,
                    107,
                    79
                ],
                [
                    125,
                    107,
                    79
                ],
                [
                    125,
                    107,
                    79
                ],
                [
                    182,
                    167,
                    140
                ],
                [
                    227,
                    216,
                    195
                ],
                [
                    0,
                    255,
                    0
                ]
            ],
            [
                [
                    0,
                    255,
                    0
                ],
                [
                    96,
                    72,
                    8
                ],
                [
                    132,
                    100,
                    44
                ],
                [
                    162,
                    144,
                    113
                ],
                [
                    136,
                    119,
                    91
                ],
                [
                    125,
                    107,
                    79
                ],
                [
                    125,
                    107,
                    79
                ],
                [
                    125,
                    107,
                    79
                ],
                [
                    154,
                    137,
                    107
                ],
                [
                    238,
                    229,
                    211
                ],
                [
                    0,
                    255,
                    0
                ]
            ],
            [
                [
                    0,
                    255,
                    0
                ],
                [
                    96,
                    72,
                    8
                ],
                [
                    132,
                    100,
                    44
                ],
                [
                    154,
                    137,
                    107
                ],
                [
                    136,
                    119,
                    91
                ],
                [
                    128,
                    113,
                    89
                ],
                [
                    125,
                    107,
                    79
                ],
                [
                    125,
                    107,
                    79
                ],
                [
                    140,
                    127,
                    108
                ],
                [
                    220,
                    209,
                    187
                ],
                [
                    0,
                    255,
                    0
                ]
            ],
            [
                [
                    0,
                    255,
                    0
                ],
                [
                    96,
                    72,
                    8
                ],
                [
                    132,
                    100,
                    44
                ],
                [
                    154,
                    137,
                    107
                ],
                [
                    140,
                    127,
                    108
                ],
                [
                    128,
                    113,
                    89
                ],
                [
                    125,
                    107,
                    79
                ],
                [
                    125,
                    107,
                    79
                ],
                [
                    128,
                    113,
                    89
                ],
                [
                    185,
                    174,
                    151
                ],
                [
                    0,
                    255,
                    0
                ]
            ],
            [
                [
                    0,
                    255,
                    0
                ],
                [
                    96,
                    72,
                    8
                ],
                [
                    125,
                    103,
                    12
                ],
                [
                    149,
                    130,
                    100
                ],
                [
                    140,
                    127,
                    108
                ],
                [
                    128,
                    113,
                    89
                ],
                [
                    128,
                    113,
                    89
                ],
                [
                    125,
                    107,
                    79
                ],
                [
                    125,
                    107,
                    79
                ],
                [
                    149,
                    138,
                    121
                ],
                [
                    0,
                    255,
                    0
                ]
            ],
            [
                [
                    0,
                    255,
                    0
                ],
                [
                    96,
                    72,
                    8
                ],
                [
                    125,
                    103,
                    12
                ],
                [
                    155,
                    120,
                    73
                ],
                [
                    140,
                    127,
                    108
                ],
                [
                    136,
                    119,
                    91
                ],
                [
                    128,
                    113,
                    89
                ],
                [
                    125,
                    107,
                    79
                ],
                [
                    128,
                    113,
                    89
                ],
                [
                    128,
                    113,
                    89
                ],
                [
                    0,
                    255,
                    0
                ]
            ],
            [
                [
                    0,
                    255,
                    0
                ],
                [
                    96,
                    72,
                    8
                ],
                [
                    132,
                    100,
                    44
                ],
                [
                    145,
                    108,
                    54
                ],
                [
                    136,
                    119,
                    91
                ],
                [
                    140,
                    127,
                    108
                ],
                [
                    128,
                    113,
                    89
                ],
                [
                    125,
                    107,
                    79
                ],
                [
                    125,
                    107,
                    79
                ],
                [
                    125,
                    107,
                    79
                ],
                [
                    0,
                    255,
                    0
                ]
            ],
            [
                [
                    0,
                    255,
                    0
                ],
                [
                    96,
                    72,
                    8
                ],
                [
                    146,
                    117,
                    32
                ],
                [
                    132,
                    100,
                    44
                ],
                [
                    120,
                    100,
                    74
                ],
                [
                    149,
                    138,
                    121
                ],
                [
                    128,
                    113,
                    89
                ],
                [
                    125,
                    107,
                    79
                ],
                [
                    125,
                    107,
                    79
                ],
                [
                    128,
                    113,
                    89
                ],
                [
                    0,
                    255,
                    0
                ]
            ],
            [
                [
                    0,
                    255,
                    0
                ],
                [
                    88,
                    63,
                    7
                ],
                [
                    132,
                    100,
                    44
                ],
                [
                    125,
                    103,
                    12
                ],
                [
                    120,
                    88,
                    37
                ],
                [
                    154,
                    137,
                    107
                ],
                [
                    136,
                    119,
                    91
                ],
                [
                    125,
                    107,
                    79
                ],
                [
                    125,
                    107,
                    79
                ],
                [
                    128,
                    113,
                    89
                ],
                [
                    0,
                    255,
                    0
                ]
            ],
            [
                [
                    0,
                    255,
                    0
                ],
                [
                    0,
                    255,
                    0
                ],
                [
                    0,
                    255,
                    0
                ],
                [
                    0,
                    255,
                    0
                ],
                [
                    0,
                    255,
                    0
                ],
                [
                    0,
                    255,
                    0
                ],
                [
                    0,
                    255,
                    0
                ],
                [
                    0,
                    255,
                    0
                ],
                [
                    0,
                    255,
                    0
                ],
                [
                    0,
                    255,
                    0
                ],
                [
                    0,
                    255,
                    0
                ]
            ]
        ]
    },
    {
        "position": [
            132,
            273
        ],
        "rgb": [
            128,
            113,
            89
        ],
        "intensity": 110.0,
        "mean_window": [
            132.23140495867767,
            113.49586776859505,
            76.01652892561984
        ],
        "std_window": [
            30.684952117541954,
            34.14870832762673,
            48.85397087848919
        ],
        "window": [
            [
                [
                    0,
                    255,
                    0
                ],
                [
                    0,
                    255,
                    0
                ],
                [
                    0,
                    255,
                    0
                ],
                [
                    0,
                    255,
                    0
                ],
                [
                    0,
                    255,
                    0
                ],
                [
                    0,
                    255,
                    0
                ],
                [
                    0,
                    255,
                    0
                ],
                [
                    0,
                    255,
                    0
                ],
                [
                    0,
                    255,
                    0
                ],
                [
                    0,
                    255,
                    0
                ],
                [
                    0,
                    255,
                    0
                ]
            ],
            [
                [
                    0,
                    255,
                    0
                ],
                [
                    96,
                    72,
                    8
                ],
                [
                    137,
                    113,
                    77
                ],
                [
                    149,
                    138,
                    121
                ],
                [
                    128,
                    113,
                    89
                ],
                [
                    125,
                    107,
                    79
                ],
                [
                    125,
                    107,
                    79
                ],
                [
                    125,
                    107,
                    79
                ],
                [
                    182,
                    167,
                    140
                ],
                [
                    227,
                    216,
                    195
                ],
                [
                    0,
                    255,
                    0
                ]
            ],
            [
                [
                    0,
                    255,
                    0
                ],
                [
                    96,
                    72,
                    8
                ],
                [
                    132,
                    100,
                    44
                ],
                [
                    162,
                    144,
                    113
                ],
                [
                    136,
                    119,
                    91
                ],
                [
                    125,
                    107,
                    79
                ],
                [
                    125,
                    107,
                    79
                ],
                [
                    125,
                    107,
                    79
                ],
                [
                    154,
                    137,
                    107
                ],
                [
                    238,
                    229,
                    211
                ],
                [
                    0,
                    255,
                    0
                ]
            ],
            [
                [
                    0,
                    255,
                    0
                ],
                [
                    96,
                    72,
                    8
                ],
                [
                    132,
                    100,
                    44
                ],
                [
                    154,
                    137,
                    107
                ],
                [
                    136,
                    119,
                    91
                ],
                [
                    128,
                    113,
                    89
                ],
                [
                    125,
                    107,
                    79
                ],
                [
                    125,
                    107,
                    79
                ],
                [
                    140,
                    127,
                    108
                ],
                [
                    220,
                    209,
                    187
                ],
                [
                    0,
                    255,
                    0
                ]
            ],
            [
                [
                    0,
                    255,
                    0
                ],
                [
                    96,
                    72,
                    8
                ],
                [
                    132,
                    100,
                    44
                ],
                [
                    154,
                    137,
                    107
                ],
                [
                    140,
                    127,
                    108
                ],
                [
                    128,
                    113,
                    89
                ],
                [
                    125,
                    107,
                    79
                ],
                [
                    125,
                    107,
                    79
                ],
                [
                    128,
                    113,
                    89
                ],
                [
                    185,
                    174,
                    151
                ],
                [
                    0,
                    255,
                    0
                ]
            ],
            [
                [
                    0,
                    255,
                    0
                ],
                [
                    96,
                    72,
                    8
                ],
                [
                    125,
                    103,
                    12
                ],
                [
                    149,
                    130,
                    100
                ],
                [
                    140,
                    127,
                    108
                ],
                [
                    128,
                    113,
                    89
                ],
                [
                    128,
                    113,
                    89
                ],
                [
                    125,
                    107,
                    79
                ],
                [
                    125,
                    107,
                    79
                ],
                [
                    149,
                    138,
                    121
                ],
                [
                    0,
                    255,
                    0
                ]
            ],
            [
                [
                    0,
                    255,
                    0
                ],
                [
                    96,
                    72,
                    8
                ],
                [
                    125,
                    103,
                    12
                ],
                [
                    155,
                    120,
                    73
                ],
                [
                    140,
                    127,
                    108
                ],
                [
                    136,
                    119,
                    91
                ],
                [
                    128,
                    113,
                    89
                ],
                [
                    125,
                    107,
                    79
                ],
                [
                    128,
                    113,
                    89
                ],
                [
                    128,
                    113,
                    89
                ],
                [
                    0,
                    255,
                    0
                ]
            ],
            [
                [
                    0,
                    255,
                    0
                ],
                [
                    96,
                    72,
                    8
                ],
                [
                    132,
                    100,
                    44
                ],
                [
                    145,
                    108,
                    54
                ],
                [
                    136,
                    119,
                    91
                ],
                [
                    140,
                    127,
                    108
                ],
                [
                    128,
                    113,
                    89
                ],
                [
                    125,
                    107,
                    79
                ],
                [
                    125,
                    107,
                    79
                ],
                [
                    125,
                    107,
                    79
                ],
                [
                    0,
                    255,
                    0
                ]
            ],
            [
                [
                    0,
                    255,
                    0
                ],
                [
                    96,
                    72,
                    8
                ],
                [
                    146,
                    117,
                    32
                ],
                [
                    132,
                    100,
                    44
                ],
                [
                    120,
                    100,
                    74
                ],
                [
                    149,
                    138,
                    121
                ],
                [
                    128,
                    113,
                    89
                ],
                [
                    125,
                    107,
                    79
                ],
                [
                    125,
                    107,
                    79
                ],
                [
                    128,
                    113,
                    89
                ],
                [
                    0,
                    255,
                    0
                ]
            ],
            [
                [
                    0,
                    255,
                    0
                ],
                [
                    88,
                    63,
                    7
                ],
                [
                    132,
                    100,
                    44
                ],
                [
                    125,
                    103,
                    12
                ],
                [
                    120,
                    88,
                    37
                ],
                [
                    154,
                    137,
                    107
                ],
                [
                    136,
                    119,
                    91
                ],
                [
                    125,
                    107,
                    79
                ],
                [
                    125,
                    107,
                    79
                ],
                [
                    128,
                    113,
                    89
                ],
                [
                    0,
                    255,
                    0
                ]
            ],
            [
                [
                    0,
                    255,
                    0
                ],
                [
                    0,
                    255,
                    0
                ],
                [
                    0,
                    255,
                    0
                ],
                [
                    0,
                    255,
                    0
                ],
                [
                    0,
                    255,
                    0
                ],
                [
                    0,
                    255,
                    0
                ],
                [
                    0,
                    255,
                    0
                ],
                [
                    0,
                    255,
                    0
                ],
                [
                    0,
                    255,
                    0
                ],
                [
                    0,
                    255,
                    0
                ],
                [
                    0,
                    255,
                    0
                ]
            ]
        ]
    },
    {
        "position": [
            129,
            277
        ],
        "rgb": [
            132,
            100,
            44
        ],
        "intensity": 92.0,
        "mean_window": [
            114.69421487603306,
            91.94214876033058,
            39.413223140495866
        ],
        "std_window": [
            20.49262837637013,
            22.552893758239357,
            38.80735838495037
        ],
        "window": [
            [
                [
                    0,
                    255,
                    0
                ],
                [
                    0,
                    255,
                    0
                ],
                [
                    0,
                    255,
                    0
                ],
                [
                    0,
                    255,
                    0
                ],
                [
                    0,
                    255,
                    0
                ],
                [
                    0,
                    255,
                    0
                ],
                [
                    0,
                    255,
                    0
                ],
                [
                    0,
                    255,
                    0
                ],
                [
                    0,
                    255,
                    0
                ],
                [
                    0,
                    255,
                    0
                ],
                [
                    0,
                    255,
                    0
                ]
            ],
            [
                [
                    0,
                    255,
                    0
                ],
                [
                    96,
                    72,
                    8
                ],
                [
                    96,
                    72,
                    8
                ],
                [
                    96,
                    72,
                    8
                ],
                [
                    96,
                    72,
                    8
                ],
                [
                    125,
                    103,
                    12
                ],
                [
                    149,
                    130,
                    100
                ],
                [
                    140,
                    127,
                    108
                ],
                [
                    128,
                    113,
                    89
                ],
                [
                    128,
                    113,
                    89
                ],
                [
                    0,
                    255,
                    0
                ]
            ],
            [
                [
                    0,
                    255,
                    0
                ],
                [
                    96,
                    72,
                    8
                ],
                [
                    96,
                    72,
                    8
                ],
                [
                    108,
                    86,
                    8
                ],
                [
                    96,
                    72,
                    8
                ],
                [
                    125,
                    103,
                    12
                ],
                [
                    155,
                    120,
                    73
                ],
                [
                    140,
                    127,
                    108
                ],
                [
                    136,
                    119,
                    91
                ],
                [
                    128,
                    113,
                    89
                ],
                [
                    0,
                    255,
                    0
                ]
            ],
            [
                [
                    0,
                    255,
                    0
                ],
                [
                    96,
                    72,
                    8
                ],
                [
                    108,
                    86,
                    8
                ],
                [
                    96,
                    72,
                    8
                ],
                [
                    96,
                    72,
                    8
                ],
                [
                    132,
                    100,
                    44
                ],
                [
                    145,
                    108,
                    54
                ],
                [
                    136,
                    119,
                    91
                ],
                [
                    140,
                    127,
                    108
                ],
                [
                    128,
                    113,
                    89
                ],
                [
                    0,
                    255,
                    0
                ]
            ],
            [
                [
                    0,
                    255,
                    0
                ],
                [
                    96,
                    72,
                    8
                ],
                [
                    96,
                    72,
                    8
                ],
                [
                    96,
                    72,
                    8
                ],
                [
                    96,
                    72,
                    8
                ],
                [
                    146,
                    117,
                    32
                ],
                [
                    132,
                    100,
                    44
                ],
                [
                    120,
                    100,
                    74
                ],
                [
                    149,
                    138,
                    121
                ],
                [
                    128,
                    113,
                    89
                ],
                [
                    0,
                    255,
                    0
                ]
            ],
            [
                [
                    0,
                    255,
                    0
                ],
                [
                    96,
                    72,
                    8
                ],
                [
                    96,
                    72,
                    8
                ],
                [
                    96,
                    72,
                    8
                ],
                [
                    88,
                    63,
                    7
                ],
                [
                    132,
                    100,
                    44
                ],
                [
                    125,
                    103,
                    12
                ],
                [
                    120,
                    88,
                    37
                ],
                [
                    154,
                    137,
                    107
                ],
                [
                    136,
                    119,
                    91
                ],
                [
                    0,
                    255,
                    0
                ]
            ],
            [
                [
                    0,
                    255,
                    0
                ],
                [
                    96,
                    72,
                    8
                ],
                [
                    96,
                    72,
                    8
                ],
                [
                    96,
                    72,
                    8
                ],
                [
                    96,
                    72,
                    8
                ],
                [
                    132,
                    100,
                    44
                ],
                [
                    125,
                    103,
                    12
                ],
                [
                    108,
                    86,
                    8
                ],
                [
                    149,
                    130,
                    100
                ],
                [
                    140,
                    127,
                    108
                ],
                [
                    0,
                    255,
                    0
                ]
            ],
            [
                [
                    0,
                    255,
                    0
                ],
                [
                    96,
                    72,
                    8
                ],
                [
                    96,
                    72,
                    8
                ],
                [
                    96,
                    72,
                    8
                ],
                [
                    88,
                    63,
                    7
                ],
                [
                    132,
                    100,
                    44
                ],
                [
                    132,
                    100,
                    44
                ],
                [
                    88,
                    63,
                    7
                ],
                [
                    137,
                    113,
                    77
                ],
                [
                    154,
                    137,
                    107
                ],
                [
                    0,
                    255,
                    0
                ]
            ],
            [
                [
                    0,
                    255,
                    0
                ],
                [
                    96,
                    72,
                    8
                ],
                [
                    96,
                    72,
                    8
                ],
                [
                    96,
                    72,
                    8
                ],
                [
                    88,
                    63,
                    7
                ],
                [
                    132,
                    100,
                    44
                ],
                [
                    132,
                    100,
                    44
                ],
                [
                    88,
                    63,
                    7
                ],
                [
                    120,
                    88,
                    37
                ],
                [
                    154,
                    137,
                    107
                ],
                [
                    0,
                    255,
                    0
                ]
            ],
            [
                [
                    0,
                    255,
                    0
                ],
                [
                    96,
                    72,
                    8
                ],
                [
                    96,
                    72,
                    8
                ],
                [
                    96,
                    72,
                    8
                ],
                [
                    88,
                    63,
                    7
                ],
                [
                    132,
                    100,
                    44
                ],
                [
                    132,
                    100,
                    44
                ],
                [
                    96,
                    72,
                    8
                ],
                [
                    108,
                    86,
                    8
                ],
                [
                    149,
                    130,
                    100
                ],
                [
                    0,
                    255,
                    0
                ]
            ],
            [
                [
                    0,
                    255,
                    0
                ],
                [
                    0,
                    255,
                    0
                ],
                [
                    0,
                    255,
                    0
                ],
                [
                    0,
                    255,
                    0
                ],
                [
                    0,
                    255,
                    0
                ],
                [
                    0,
                    255,
                    0
                ],
                [
                    0,
                    255,
                    0
                ],
                [
                    0,
                    255,
                    0
                ],
                [
                    0,
                    255,
                    0
                ],
                [
                    0,
                    255,
                    0
                ],
                [
                    0,
                    255,
                    0
                ]
            ]
        ]
    }
]